topsis/__init__.py
topsis/topsis.py
Topsis_AbhayKansal_101903685-1.0.0.dist-info/LICENSE
Topsis_AbhayKansal_101903685-1.0.0.dist-info/METADATA
Topsis_AbhayKansal_101903685-1.0.0.dist-info/WHEEL
Topsis_AbhayKansal_101903685-1.0.0.dist-info/top_level.txt
Topsis_AbhayKansal_101903685-1.0.0.dist-info/RECORD
